quTARANG/IO.py
quTARANG/__init__.py
quTARANG/evolution.py
quTARANG/gpe.py
quTARANG/univ/__init__.py
quTARANG/univ/fns.py
quTARANG/univ/grid.py
quTARANG/univ/my_fft.py
quTARANG/univ/params.py
qutarang-0.0.1.dist-info/METADATA
qutarang-0.0.1.dist-info/WHEEL
qutarang-0.0.1.dist-info/licenses/LICENSE
qutarang-0.0.1.dist-info/RECORD
