Metadata-Version: 2.1
Name: quTARANG
Version: 0.0.1
Summary: GPE solver
Project-URL: Homepage, https://github.com/sachinrawat2207/quTARANG
Project-URL: Bug Tracker, https://github.com/sachinrawat2207/quTARANG/issues
Author-email: Shawan Kumar Jha <shawankumar@iitg.ac.in>, Sachin Singh Rawat <sachinr@iitk.ac.in>
License-File: LICENSE
Classifier: Development Status :: 5 - Production/Stable
Classifier: Operating System :: OS Independent
Classifier: Programming Language :: Python :: 3
Requires-Python: >=3.7
